gfunction_auth/__init__.py
gfunction_auth-0.0.4.dist-info/METADATA
gfunction_auth-0.0.4.dist-info/WHEEL
gfunction_auth-0.0.4.dist-info/top_level.txt
gfunction_auth-0.0.4.dist-info/RECORD
