Metadata-Version: 2.1
Name: gfunction-auth
Version: 0.0.4
Summary: A lightweight package for makeing authorized requests to Google Cloud Functions.
Home-page: https://github.com/andrewdircks/gfunctions-auth
Author: Andrew Dircks
Author-email: abd93@cornell.edu
License: UNKNOWN
Platform: UNKNOWN
Classifier: Programming Language :: Python :: 3
Classifier: Operating System :: OS Independent
Requires-Python: >=3.7
Requires-Dist: requests
Requires-Dist: google-auth
Requires-Dist: google-oauth
